iotedge_driver_link_sdk-0.2.0.dist-info/DESCRIPTION.rst
iotedge_driver_link_sdk-0.2.0.dist-info/METADATA
iotedge_driver_link_sdk-0.2.0.dist-info/RECORD
iotedge_driver_link_sdk-0.2.0.dist-info/WHEEL
iotedge_driver_link_sdk-0.2.0.dist-info/metadata.json
iotedge_driver_link_sdk-0.2.0.dist-info/top_level.txt
iotedgedriverlinksdk/__init__.py
iotedgedriverlinksdk/client.py
iotedgedriverlinksdk/edge.py
iotedgedriverlinksdk/exception.py
iotedgedriverlinksdk/nats.py
