Metadata-Version: 2.0
Name: iotedge-driver-link-sdk
Version: 0.2.0
Summary: IoT Edge Driver Link SDK
Home-page: https://pypi.org/project/iotedge_driver_link_sdk/
Author: ucloud.cn
Author-email: joy.zhou@ucloud.cn
License: Apache 2 License
Platform: any
Requires-Dist: asyncio-nats-client (>=0.10.0)
Requires-Dist: cachetools (>=4.0.0)
